winpwn/__init__.py
winpwn/context.py
winpwn/dbg.py
winpwn/misc.py
winpwn/var.py
winpwn/win.py
winpwn/winpwn.py
anpwn-0.0.1.dist-info/METADATA
anpwn-0.0.1.dist-info/WHEEL
anpwn-0.0.1.dist-info/top_level.txt
anpwn-0.0.1.dist-info/RECORD
